meta_permissions/__init__.py
meta_permissions/apps.py
meta_permissions/codenames_by_group.py
meta_permissions/urls.py
meta_permissions/codenames/__init__.py
meta_permissions/codenames/auditor.py
meta_permissions/codenames/clinic.py
meta_permissions/codenames/screening.py
meta_permissions/codenames/unblinding.py
meta_permissions/tests/__init__.py
meta_permissions/tests/test_permissions.py
meta_permissions/tests/urls.py
meta_permissions-0.1.8.dist-info/AUTHORS
meta_permissions-0.1.8.dist-info/LICENSE
meta_permissions-0.1.8.dist-info/METADATA
meta_permissions-0.1.8.dist-info/WHEEL
meta_permissions-0.1.8.dist-info/top_level.txt
meta_permissions-0.1.8.dist-info/RECORD
